{
    "Background": {
        "$PPIE": 16,
        "Bluish": 237,
        "Cosmos": 52,
        "Disco": 130,
        "Forest": 151,
        "GOD": 4,
        "Grayish": 223,
        "Greenish": 557,
        "Haunted": 63,
        "Inferno": 145,
        "Midnight": 209,
        "Pinkish": 543,
        "Pumpkin Patch": 140,
        "Purplish": 245,
        "Stormy": 112,
        "Trippy": 228,
        "Wen Moon": 32
    },
    "Body": {
        "Bloody": 451,
        "Diamond": 26,
        "GOD": 4,
        "Ghost": 146,
        "Golden": 73,
        "None": 681,
        "Paper": 480,
        "Pixels": 189,
        "Royal Oak": 495,
        "Wen Moon": 75,
        "Zombie": 467
    },
    "Eyes": {
        "$AVAX": 28,
        "$BTC": 29,
        "$ETH": 31,
        "Ahegao": 114,
        "Anime": 122,
        "Clown": 110,
        "Diamond": 41,
        "Envy": 79,
        "Fire": 103,
        "GOD": 4,
        "Googly": 175,
        "Gummy": 55,
        "Laser": 73,
        "Nerd": 145,
        "None": 1176,
        "Odin": 31,
        "Pilot": 97,
        "Pixels": 112,
        "Red Kitty": 217,
        "Ser": 102,
        "Yellow Kitty": 243
    },
    "Facial": {
        "$POTN": 43,
        "Bubble": 98,
        "Cigar": 57,
        "GOD": 4,
        "Gingivitis": 63,
        "Lick": 43,
        "Lollipop": 60,
        "Monster": 32,
        "Mustache": 325,
        "None": 1286,
        "Orc": 311,
        "Pipe": 320,
        "Popsicle": 33,
        "Stoner": 54,
        "The Count": 42,
        "Zeus": 316
    },
    "Frame": {
        "Diamond": 61,
        "Flames": 91,
        "GOD": 4,
        "Hedge": 44,
        "None": 2626,
        "Renaissance": 117,
        "Runes": 144
    },
    "Head": {
        "$AVAX": 30,
        "$BTC": 29,
        "$ETH": 20,
        "All Seeing": 54,
        "Artiste": 25,
        "Baseman": 19,
        "Bathing": 69,
        "Big Brains": 34,
        "Bullish": 6,
        "Cap": 88,
        "Chef": 58,
        "Comrade": 76,
        "Cowboy": 60,
        "Cyborg": 37,
        "DJ": 75,
        "Demon": 72,
        "Fallen Angel": 76,
        "Fedora": 35,
        "Fireman": 34,
        "Frankenstein": 71,
        "GOD": 4,
        "Gamer": 68,
        "Glittery": 67,
        "Grad": 80,
        "HODL": 38,
        "Hombre": 11,
        "Jester": 81,
        "Judge": 42,
        "None": 822,
        "Oh Deer..": 48,
        "Papa": 41,
        "Pink _ Gold Cap": 77,
        "Pink _ Gold Fedora": 38,
        "Pot Head": 76,
        "Pride": 21,
        "Psych Cap": 82,
        "Psych Chef": 44,
        "Psych Cowboy": 37,
        "Psych Ser": 33,
        "Rasta": 35,
        "Ronin": 42,
        "Samurai": 11,
        "Steel Ser": 74,
        "Unicorn": 21,
        "Valhalla": 76,
        "WAGMI": 33,
        "WcDonald_s": 9,
        "Weee": 12,
        "Wen Moon": 77,
        "Wizard": 13,
        "pumpsKing": 6
    },
    "Item": {
        "$POTN": 35,
        "$PPIE": 41,
        "Bats": 162,
        "Bullish": 95,
        "Butterflies": 51,
        "En garde": 155,
        "GOD": 4,
        "Holy Grail": 60,
        "Huginn _ Muninn": 19,
        "In the Den": 95,
        "Mace": 58,
        "None": 1225,
        "Oracle": 75,
        "Pitchfork": 154,
        "Reaper": 169,
        "Rock n_ Roll": 92,
        "Samurai": 152,
        "Torch": 172,
        "Viking": 94,
        "Wen Lambo": 48,
        "Whaling": 26,
        "Wizard": 105
    },
    "Neck": {
        "Bling": 75,
        "Blue Tie": 213,
        "Business": 122,
        "Chained": 83,
        "GOD": 4,
        "Hero": 247,
        "None": 930,
        "Rugged": 298,
        "Shaman": 254,
        "Smoked": 319,
        "Wood Tie": 178,
        "Zeus": 364
    }
}